jackknify/ImSettings.py
jackknify/Main.py
jackknify/MsManager.py
jackknify/Plot.py
jackknify/__init__.py
jackknify/io.py
jackknify-0.3.0.dist-info/LICENSE
jackknify-0.3.0.dist-info/METADATA
jackknify-0.3.0.dist-info/WHEEL
jackknify-0.3.0.dist-info/top_level.txt
jackknify-0.3.0.dist-info/RECORD
