Metadata-Version: 2.1
Name: jackknify
Version: 0.3.0
Summary: Jackknifing interferometric datasets
Home-page: https://github.com/Joshiwavm/jackknify
Author: Joshiwa van Marrewijk
Author-email: joshiwa01@gmail.com
License: UNKNOWN
Platform: UNKNOWN
License-File: LICENSE
Requires-Dist: astropy
Requires-Dist: casatasks
Requires-Dist: casatools
Requires-Dist: casadata
Requires-Dist: jupyterlab
Requires-Dist: matplotlib
Requires-Dist: numpy
Requires-Dist: scipy
Requires-Dist: tqdm
